AUTHORS
CHANGELOG.txt
DESCRIPTION
LICENSE
MANIFEST.in
README.rst
setup.cfg
setup.py
ad_rotator/__init__.py
ad_rotator/admin.py
ad_rotator/models.py
ad_rotator/urls.py
ad_rotator/views.py
ad_rotator/migrations/0001_initial.py
ad_rotator/migrations/__init__.py
ad_rotator/static/.empty
ad_rotator/static/ad_rotator/.empty
ad_rotator/templates/ad_rotator/.empty
ad_rotator/templates/ad_rotator/partials/banner.html
ad_rotator/templatetags/__init__.py
ad_rotator/templatetags/ad_rotator_tags.py
ad_rotator/tests/.coveragerc
ad_rotator/tests/__init__.py
ad_rotator/tests/ad_rotator_tags_tests.py
ad_rotator/tests/factories.py
ad_rotator/tests/models_tests.py
ad_rotator/tests/runtests.py
ad_rotator/tests/south_settings.py
ad_rotator/tests/test_settings.py
ad_rotator/tests/urls.py
ad_rotator/tests/test_app/__init__.py
ad_rotator/tests/test_app/models.py
ad_rotator/tests/test_app/templates/400.html
ad_rotator/tests/test_app/templates/500.html
django_ad_rotator.egg-info/PKG-INFO
django_ad_rotator.egg-info/SOURCES.txt
django_ad_rotator.egg-info/dependency_links.txt
django_ad_rotator.egg-info/requires.txt
django_ad_rotator.egg-info/top_level.txt