Metadata-Version: 1.0
Name: django-ad-rotator
Version: 0.1
Summary: A reusable Django app for managing and displaying banner ads.
